rtex/__init__.py
rtex/client.py
rtex/constants.py
rtex/exceptions.py
rtex/models.py
rtex-0.0.7.dist-info/licenses/LICENSE
rtex-0.0.7.dist-info/METADATA
rtex-0.0.7.dist-info/WHEEL
rtex-0.0.7.dist-info/top_level.txt
rtex-0.0.7.dist-info/RECORD
