Metadata-Version: 2.4
Name: rtex
Version: 0.0.7
Summary: *Unofficial* client for the Rtex API server
Author-email: Estelle Poulin <dev@inspiredby.es>
License: MIT
Project-URL: homepage, https://github.com/estheruary/python-rtex
Project-URL: repository, https://github.com/estheruary/python-rtex
Project-URL: changelog, https://github.com/estheruary/python-rtex/-/blob/main/CHANGELOG.md
Keywords: rtex,latex,math
Classifier: Programming Language :: Python :: 3
Requires-Python: >=3.11
License-File: LICENSE
Requires-Dist: aiohttp>=3.0.0
Requires-Dist: pydantic>=2.0.0
Dynamic: license-file
